{"note":"This file is an internal implementation detail to speed up HTML report generation. Its format can change at any time. You might be looking for the JSON report: https://coverage.rtfd.io/cmd.html#cmd-json","format":5,"version":"7.10.7","globals":"e3ffba44eac8a51cf9a4e12f6feab44e","files":{"z_1ea838694151cac8___init___py":{"hash":"e6baa73cda2916dad605215f937a92e1","index":{"url":"z_1ea838694151cac8___init___py.html","file":"config\\__init__.py","description":"","nums":{"precision":0,"n_files":1,"n_statements":0,"n_excluded":0,"n_missing":0,"n_branches":0,"n_partial_branches":0,"n_missing_branches":0}}},"z_1ea838694151cac8_settings_py":{"hash":"9efd3f129a5782d4cd9413ca924fbf79","index":{"url":"z_1ea838694151cac8_settings_py.html","file":"config\\settings.py","description":"","nums":{"precision":0,"n_files":1,"n_statements":25,"n_excluded":0,"n_missing":0,"n_branches":0,"n_partial_branches":0,"n_missing_branches":0}}},"z_1ea838694151cac8_urls_py":{"hash":"76e20d5013060761743831a76e240547","index":{"url":"z_1ea838694151cac8_urls_py.html","file":"config\\urls.py","description":"","nums":{"precision":0,"n_files":1,"n_statements":9,"n_excluded":0,"n_missing":0,"n_branches":0,"n_partial_branches":0,"n_missing_branches":0}}},"manage_py":{"hash":"18debec8f939d2d921a9ea1ca90aa845","index":{"url":"manage_py.html","file":"manage.py","description":"","nums":{"precision":0,"n_files":1,"n_statements":11,"n_excluded":0,"n_missing":2,"n_branches":0,"n_partial_branches":0,"n_missing_branches":0}}},"z_f978324627c06562___init___py":{"hash":"e6baa73cda2916dad605215f937a92e1","index":{"url":"z_f978324627c06562___init___py.html","file":"materials\\__init__.py","description":"","nums":{"precision":0,"n_files":1,"n_statements":0,"n_excluded":0,"n_missing":0,"n_branches":0,"n_partial_branches":0,"n_missing_branches":0}}},"z_f978324627c06562_admin_py":{"hash":"3802db8fabfa3de6e97cdd70b6ce5d34","index":{"url":"z_f978324627c06562_admin_py.html","file":"materials\\admin.py","description":"","nums":{"precision":0,"n_files":1,"n_statements":11,"n_excluded":0,"n_missing":0,"n_branches":0,"n_partial_branches":0,"n_missing_branches":0}}},"z_f978324627c06562_apps_py":{"hash":"bc2f274c3f0788315d32fbbcbe243c6f","index":{"url":"z_f978324627c06562_apps_py.html","file":"materials\\apps.py","description":"","nums":{"precision":0,"n_files":1,"n_statements":4,"n_excluded":0,"n_missing":0,"n_branches":0,"n_partial_branches":0,"n_missing_branches":0}}},"z_2484c951eaf88dd9_0001_initial_py":{"hash":"b4fb1edb6a2a7155f9c3ea0608a5329d","index":{"url":"z_2484c951eaf88dd9_0001_initial_py.html","file":"materials\\migrations\\0001_initial.py","description":"","nums":{"precision":0,"n_files":1,"n_statements":6,"n_excluded":0,"n_missing":0,"n_branches":0,"n_partial_branches":0,"n_missing_branches":0}}},"z_2484c951eaf88dd9_0002_alter_course_options_alter_lesson_options_and_more_py":{"hash":"90529a60fcca1bbbf2e007ec4f3c3dc1","index":{"url":"z_2484c951eaf88dd9_0002_alter_course_options_alter_lesson_options_and_more_py.html","file":"materials\\migrations\\0002_alter_course_options_alter_lesson_options_and_more.py","description":"","nums":{"precision":0,"n_files":1,"n_statements":5,"n_excluded":0,"n_missing":0,"n_branches":0,"n_partial_branches":0,"n_missing_branches":0}}},"z_2484c951eaf88dd9_0003_course_owner_lesson_owner_py":{"hash":"1fa2bc637eb3bad6d9513b7dd0b45ae4","index":{"url":"z_2484c951eaf88dd9_0003_course_owner_lesson_owner_py.html","file":"materials\\migrations\\0003_course_owner_lesson_owner.py","description":"","nums":{"precision":0,"n_files":1,"n_statements":6,"n_excluded":0,"n_missing":0,"n_branches":0,"n_partial_branches":0,"n_missing_branches":0}}},"z_2484c951eaf88dd9_0004_subscription_py":{"hash":"844b9e84131213ff3e459505610facd5","index":{"url":"z_2484c951eaf88dd9_0004_subscription_py.html","file":"materials\\migrations\\0004_subscription.py","description":"","nums":{"precision":0,"n_files":1,"n_statements":6,"n_excluded":0,"n_missing":0,"n_branches":0,"n_partial_branches":0,"n_missing_branches":0}}},"z_2484c951eaf88dd9___init___py":{"hash":"e6baa73cda2916dad605215f937a92e1","index":{"url":"z_2484c951eaf88dd9___init___py.html","file":"materials\\migrations\\__init__.py","description":"","nums":{"precision":0,"n_files":1,"n_statements":0,"n_excluded":0,"n_missing":0,"n_branches":0,"n_partial_branches":0,"n_missing_branches":0}}},"z_f978324627c06562_models_py":{"hash":"f66d0b680840f2d2e3204d635039f631","index":{"url":"z_f978324627c06562_models_py.html","file":"materials\\models.py","description":"","nums":{"precision":0,"n_files":1,"n_statements":36,"n_excluded":0,"n_missing":3,"n_branches":0,"n_partial_branches":0,"n_missing_branches":0}}},"z_f978324627c06562_serializers_py":{"hash":"897bb45e33ed5bf396d35957bb65a243","index":{"url":"z_f978324627c06562_serializers_py.html","file":"materials\\serializers.py","description":"","nums":{"precision":0,"n_files":1,"n_statements":29,"n_excluded":0,"n_missing":5,"n_branches":0,"n_partial_branches":0,"n_missing_branches":0}}},"z_f978324627c06562_tests_py":{"hash":"275ceadf65546f09197f4158446a67a7","index":{"url":"z_f978324627c06562_tests_py.html","file":"materials\\tests.py","description":"","nums":{"precision":0,"n_files":1,"n_statements":61,"n_excluded":0,"n_missing":1,"n_branches":0,"n_partial_branches":0,"n_missing_branches":0}}},"z_f978324627c06562_urls_py":{"hash":"933b6e17fe669168a8ba0c58924b60a9","index":{"url":"z_f978324627c06562_urls_py.html","file":"materials\\urls.py","description":"","nums":{"precision":0,"n_files":1,"n_statements":3,"n_excluded":0,"n_missing":0,"n_branches":0,"n_partial_branches":0,"n_missing_branches":0}}},"z_f978324627c06562_validators_py":{"hash":"7be7acb31f04af26089681c9706484ce","index":{"url":"z_f978324627c06562_validators_py.html","file":"materials\\validators.py","description":"","nums":{"precision":0,"n_files":1,"n_statements":6,"n_excluded":0,"n_missing":1,"n_branches":0,"n_partial_branches":0,"n_missing_branches":0}}},"z_f978324627c06562_views_py":{"hash":"5995b6fd826fda97427dc4262a9fc265","index":{"url":"z_f978324627c06562_views_py.html","file":"materials\\views.py","description":"","nums":{"precision":0,"n_files":1,"n_statements":77,"n_excluded":0,"n_missing":21,"n_branches":0,"n_partial_branches":0,"n_missing_branches":0}}},"z_f6c68bdc9becfc1e___init___py":{"hash":"e6baa73cda2916dad605215f937a92e1","index":{"url":"z_f6c68bdc9becfc1e___init___py.html","file":"users\\__init__.py","description":"","nums":{"precision":0,"n_files":1,"n_statements":0,"n_excluded":0,"n_missing":0,"n_branches":0,"n_partial_branches":0,"n_missing_branches":0}}},"z_f6c68bdc9becfc1e_admin_py":{"hash":"c24e8c95af7a8447b379ecea12ff6990","index":{"url":"z_f6c68bdc9becfc1e_admin_py.html","file":"users\\admin.py","description":"","nums":{"precision":0,"n_files":1,"n_statements":1,"n_excluded":0,"n_missing":0,"n_branches":0,"n_partial_branches":0,"n_missing_branches":0}}},"z_f6c68bdc9becfc1e_apps_py":{"hash":"ef09ad02db0d7217b814a169a66a26f9","index":{"url":"z_f6c68bdc9becfc1e_apps_py.html","file":"users\\apps.py","description":"","nums":{"precision":0,"n_files":1,"n_statements":4,"n_excluded":0,"n_missing":0,"n_branches":0,"n_partial_branches":0,"n_missing_branches":0}}},"z_fff39e3ca0aaeed4_0001_initial_py":{"hash":"8815d5a3d4d45a387114de0b4e455eb4","index":{"url":"z_fff39e3ca0aaeed4_0001_initial_py.html","file":"users\\migrations\\0001_initial.py","description":"","nums":{"precision":0,"n_files":1,"n_statements":7,"n_excluded":0,"n_missing":0,"n_branches":0,"n_partial_branches":0,"n_missing_branches":0}}},"z_fff39e3ca0aaeed4_0002_alter_user_managers_py":{"hash":"a112e0ab53fe24b0c9cf044f6d4bf4b3","index":{"url":"z_fff39e3ca0aaeed4_0002_alter_user_managers_py.html","file":"users\\migrations\\0002_alter_user_managers.py","description":"","nums":{"precision":0,"n_files":1,"n_statements":4,"n_excluded":0,"n_missing":0,"n_branches":0,"n_partial_branches":0,"n_missing_branches":0}}},"z_fff39e3ca0aaeed4_0003_alter_user_options_alter_user_avatar_alter_user_city_and_more_py":{"hash":"2b32ad3c2aaf5501bae26a19775c2004","index":{"url":"z_fff39e3ca0aaeed4_0003_alter_user_options_alter_user_avatar_alter_user_city_and_more_py.html","file":"users\\migrations\\0003_alter_user_options_alter_user_avatar_alter_user_city_and_more.py","description":"","nums":{"precision":0,"n_files":1,"n_statements":6,"n_excluded":0,"n_missing":0,"n_branches":0,"n_partial_branches":0,"n_missing_branches":0}}},"z_fff39e3ca0aaeed4___init___py":{"hash":"e6baa73cda2916dad605215f937a92e1","index":{"url":"z_fff39e3ca0aaeed4___init___py.html","file":"users\\migrations\\__init__.py","description":"","nums":{"precision":0,"n_files":1,"n_statements":0,"n_excluded":0,"n_missing":0,"n_branches":0,"n_partial_branches":0,"n_missing_branches":0}}},"z_f6c68bdc9becfc1e_models_py":{"hash":"dd206f75c576988f57ca7cb15f2747fa","index":{"url":"z_f6c68bdc9becfc1e_models_py.html","file":"users\\models.py","description":"","nums":{"precision":0,"n_files":1,"n_statements":48,"n_excluded":0,"n_missing":10,"n_branches":0,"n_partial_branches":0,"n_missing_branches":0}}},"z_f6c68bdc9becfc1e_permissions_py":{"hash":"7555e3f779d84f99b9afe0ec83c1ea48","index":{"url":"z_f6c68bdc9becfc1e_permissions_py.html","file":"users\\permissions.py","description":"","nums":{"precision":0,"n_files":1,"n_statements":13,"n_excluded":0,"n_missing":2,"n_branches":0,"n_partial_branches":0,"n_missing_branches":0}}},"z_f6c68bdc9becfc1e_tests_py":{"hash":"c313beeff07856558e508f67092c9510","index":{"url":"z_f6c68bdc9becfc1e_tests_py.html","file":"users\\tests.py","description":"","nums":{"precision":0,"n_files":1,"n_statements":1,"n_excluded":0,"n_missing":0,"n_branches":0,"n_partial_branches":0,"n_missing_branches":0}}}}}